gcommon/__init__.py
gcommon/helpers.py
gcommon/aio/__init__.py
gcommon/aio/gaiohttp.py
gcommon/aio/gasync.py
gcommon/aio/gflask.py
gcommon/aio/gmonitor.py
gcommon/aio/grpc_utils.py
gcommon/aio/gserver.py
gcommon/aio/gtask.py
gcommon/aio/gtimer.py
gcommon/aio/restapi.py
gcommon/aio/webclient.py
gcommon/aio/ws_server.py
gcommon/aio/cluster/__init__.py
gcommon/aio/cluster/cluster_client.py
gcommon/aio/cluster/cluster_config.py
gcommon/aio/cluster/cluster_manager.py
gcommon/aio/cluster/cluster_server.py
gcommon/aio/cluster/cluster_status.py
gcommon/aio/cluster/external_service.py
gcommon/aio/cluster/zk_client.py
gcommon/aio/cluster/zk_helper.py
gcommon/aio/cluster/zk_service.py
gcommon/aio/cluster/allocator/__init__.py
gcommon/aio/cluster/allocator/hash_ring_allocator.py
gcommon/aio/cluster/allocator/mod_allocator.py
gcommon/aio/cluster/test/__init__.py
gcommon/aio/cluster/test/test_cluster_client.py
gcommon/aio/cluster/test/test_cluster_server.py
gcommon/aio/cluster/test/test_cluster_service.py
gcommon/aio/cluster/test/test_kazoo.py
gcommon/aio/cluster/test/test_zookeeper.py
gcommon/aio/grpc/__init__.py
gcommon/aio/grpc/grpc_proxy.py
gcommon/aio/grpc/test_grpc_proxy_client.py
gcommon/aio/grpc/test_grpc_proxy_server.py
gcommon/aio/grpc/test_grpc_server.py
gcommon/aio/grpc/proto/__init__.py
gcommon/aio/grpc/proto/helloworld_pb2.py
gcommon/aio/grpc/proto/helloworld_pb2_grpc.py
gcommon/aio/kafka/__init__.py
gcommon/aio/kafka/gkafka.py
gcommon/aio/kafka/test_aio_kafka.py
gcommon/aio/kafka/test_gkafka.py
gcommon/aio/mqtt/__init__.py
gcommon/aio/mqtt/mqtt_client.py
gcommon/aio/mqtt/mqtt_listener.py
gcommon/aio/mqtt/mqtt_thread_listener.py
gcommon/aio/mqtt/test_mqtt_listener.py
gcommon/aio/mqtt/test_mqtt_thread_listener.py
gcommon/aio/test/__init__.py
gcommon/aio/test/test_async_event.py
gcommon/aio/test/test_gasync.py
gcommon/aio/test/test_gtimer.py
gcommon/aio/test/test_gtimer_error.py
gcommon/aio/test/test_web_server.py
gcommon/aio/test/test_webclient.py
gcommon-1.1.3.dist-info/LICENSE
gcommon-1.1.3.dist-info/METADATA
gcommon-1.1.3.dist-info/WHEEL
gcommon-1.1.3.dist-info/entry_points.txt
gcommon-1.1.3.dist-info/top_level.txt
gcommon-1.1.3.dist-info/RECORD
