Metadata-Version: 2.1
Name: gcommon
Version: 1.1.3
Summary: Common Python Library for server and client application.
Home-page: https://github.com/liguopeng80/gcommon
Author: Guo Peng Li
Author-email: liguopeng@liguopeng.net
License: MIT
Classifier: License :: OSI Approved :: MIT License
Classifier: Topic :: Utilities
Classifier: Programming Language :: Python
Requires-Python: >=3.7, <4
License-File: LICENSE
Requires-Dist: aiofiles ==0.8.0
Requires-Dist: aiohttp ==3.8.1
Requires-Dist: aiosignal ==1.2.0
Requires-Dist: async-timeout ==4.0.2
Requires-Dist: attrs ==21.4.0
Requires-Dist: blinker ==1.4
Requires-Dist: certifi ==2020.6.20
Requires-Dist: cffi ==1.15.0
Requires-Dist: charset-normalizer ==2.0.10
Requires-Dist: click ==8.0.3
Requires-Dist: cryptography ==36.0.1
Requires-Dist: frozenlist ==1.2.0
Requires-Dist: greenlet ==1.1.2
Requires-Dist: h11 ==0.12.0
Requires-Dist: h2 ==4.1.0
Requires-Dist: hpack ==4.0.0
Requires-Dist: hypercorn ==0.13.2
Requires-Dist: hyperframe ==6.0.1
Requires-Dist: idna ==3.3
Requires-Dist: itsdangerous ==2.0.1
Requires-Dist: Jinja2 ==3.0.3
Requires-Dist: MarkupSafe ==2.0.1
Requires-Dist: multidict ==5.2.0
Requires-Dist: priority ==2.0.0
Requires-Dist: pycparser ==2.21
Requires-Dist: pyOpenSSL ==21.0.0
Requires-Dist: python-dateutil ==2.8.2
Requires-Dist: pytz ==2021.3
Requires-Dist: PyYAML ==6.0
Requires-Dist: quart ==0.16.2
Requires-Dist: six ==1.16.0
Requires-Dist: SQLAlchemy ==1.4.29
Requires-Dist: toml ==0.10.2
Requires-Dist: Werkzeug ==2.0.2
Requires-Dist: wsproto ==1.0.0
Requires-Dist: yarl ==1.7.2
